LICENSE.txt
README.md
setup.py
discogs_scraper/__init__.py
discogs_scraper/discogScraper.py
discogs_scraper.egg-info/PKG-INFO
discogs_scraper.egg-info/SOURCES.txt
discogs_scraper.egg-info/dependency_links.txt
discogs_scraper.egg-info/requires.txt
discogs_scraper.egg-info/top_level.txt