Metadata-Version: 2.1
Name: discogs_scraper
Version: 0.11
Summary: Scrapes discogs website based on urls and then outputs csv
Home-page: https://github.com/casperUoS/discogs-Scraper
Download-URL: https://github.com/casperUoS/discogs-Scraper/archive/refs/tags/0.7.tar.gz
Author: Casper Dancy
Author-email: casperdancy@gmail.com
License: MIT
Keywords: SOME,MEANINGFULL,KEYWORDS
Classifier: Development Status :: 3 - Alpha
Classifier: Topic :: Software Development :: Build Tools
Classifier: License :: OSI Approved :: MIT License
Classifier: Programming Language :: Python :: 3
Classifier: Programming Language :: Python :: 3.4
Classifier: Programming Language :: Python :: 3.5
Classifier: Programming Language :: Python :: 3.6
License-File: LICENSE.txt
Requires-Dist: discogs_client
